wq/db/__init__.py
wq/db/rest/__init__.py
wq/db/rest/apps.py
wq/db/rest/exceptions.py
wq/db/rest/filters.py
wq/db/rest/maps.py
wq/db/rest/models.py
wq/db/rest/negotiation.py
wq/db/rest/pagination.py
wq/db/rest/permissions.py
wq/db/rest/renderers.py
wq/db/rest/routers.py
wq/db/rest/serializers.py
wq/db/rest/views.py
wq/db/rest/auth/__init__.py
wq/db/rest/auth/apps.py
wq/db/rest/auth/rest.py
wq/db/rest/auth/serializers.py
wq/db/rest/auth/views.py
wq/db/rest/management/__init__.py
wq/db/rest/management/commands/__init__.py
wq/db/rest/management/commands/dump_config.py
wq.db-2.1.0.dist-info/LICENSE
wq.db-2.1.0.dist-info/METADATA
wq.db-2.1.0.dist-info/WHEEL
wq.db-2.1.0.dist-info/entry_points.txt
wq.db-2.1.0.dist-info/top_level.txt
wq.db-2.1.0.dist-info/RECORD
