Metadata-Version: 2.1
Name: wq.db
Version: 2.1.0
Summary: Django REST API for offline mobile surveys and field data collection.
Author-email: "S. Andrew Sheppard" <andrew@wq.io>
License: MIT
Project-URL: Homepage, https://wq.io/wq.db/
Project-URL: Documentation, https://wq.io/
Project-URL: Source, https://github.com/wq/wq.db
Project-URL: Release Notes, https://github.com/wq/wq.db/releases
Project-URL: Issues, https://github.com/wq/wq.db/issues
Project-URL: Tests, https://github.com/wq/wq.db/actions/workflows/test.yml
Classifier: Development Status :: 5 - Production/Stable
Classifier: Environment :: Web Environment
Classifier: License :: OSI Approved :: MIT License
Classifier: Natural Language :: English
Classifier: Programming Language :: Python :: 3
Classifier: Programming Language :: Python :: 3.8
Classifier: Programming Language :: Python :: 3.9
Classifier: Programming Language :: Python :: 3.10
Classifier: Programming Language :: Python :: 3.11
Classifier: Programming Language :: Python :: 3.12
Classifier: Framework :: Django
Classifier: Framework :: Django :: 4.0
Classifier: Framework :: Django :: 4.1
Classifier: Framework :: Django :: 4.2
Classifier: Framework :: Django :: 5.0
Classifier: Topic :: Software Development :: Libraries :: Application Frameworks
Classifier: Topic :: Text Processing :: Markup :: HTML
Classifier: Topic :: Scientific/Engineering :: GIS
Classifier: Topic :: Database :: Database Engines/Servers
Requires-Python: >=3.8
License-File: LICENSE
Requires-Dist: Django <6.0,>=4.0
Requires-Dist: djangorestframework <4.0,>=3.14.0
Requires-Dist: html-json-forms
Requires-Dist: natural-keys >=2.1.1
Requires-Dist: drf-writable-nested
Requires-Dist: pystache
